flomo/__init__.py
flomo/beep.mp3
flomo/cli.py
flomo/config.py
flomo/errors.py
flomo/helpers.py
flomo/session_id.dll
flomo/session_id.dylib
flomo/session_id.so
flomo/tracker.py
flomo/ui.py
flomodoro-1.2.1.dist-info/licenses/LICENSE
flomodoro-1.2.1.dist-info/METADATA
flomodoro-1.2.1.dist-info/WHEEL
flomodoro-1.2.1.dist-info/entry_points.txt
flomodoro-1.2.1.dist-info/top_level.txt
flomodoro-1.2.1.dist-info/RECORD
