Metadata-Version: 2.4
Name: flomodoro
Version: 1.2.1
Summary: A Flowmodoro Timer CLI for producitivity enthusiasts.
Home-page: https://github.com/moiSentineL/flomo
Author: Dark Circles
Author-email: <nibir@nibirsan.org>, <jonakadiptakalita@gmail.com>, <anubhavnath60@gmail.com>
Keywords: cli,productivity,cli-application
Classifier: Development Status :: 5 - Production/Stable
Classifier: License :: OSI Approved :: MIT License
Classifier: Natural Language :: English
Classifier: Operating System :: OS Independent
Classifier: Intended Audience :: Developers
Classifier: Programming Language :: Python :: 3
License-File: LICENSE
Requires-Dist: click
Requires-Dist: blessed
Requires-Dist: rich
Requires-Dist: playsound==1.2.2
Requires-Dist: click-aliases
Dynamic: author
Dynamic: author-email
Dynamic: classifier
Dynamic: description
Dynamic: description-content-type
Dynamic: home-page
Dynamic: keywords
Dynamic: license-file
Dynamic: requires-dist
Dynamic: summary
